__init__.py
zoho_creator_sdk/__init__.py
zoho_creator_sdk/auth.py
zoho_creator_sdk/client.py
zoho_creator_sdk/config.py
zoho_creator_sdk/constants.py
zoho_creator_sdk/exceptions.py
zoho_creator_sdk/py.typed
zoho_creator_sdk/models/__init__.py
zoho_creator_sdk/models/base.py
zoho_creator_sdk/models/bulk_operations.py
zoho_creator_sdk/models/config.py
zoho_creator_sdk/models/connection.py
zoho_creator_sdk/models/core.py
zoho_creator_sdk/models/criteria.py
zoho_creator_sdk/models/custom_action.py
zoho_creator_sdk/models/enums.py
zoho_creator_sdk/models/forms.py
zoho_creator_sdk/models/import_export.py
zoho_creator_sdk/models/metadata.py
zoho_creator_sdk/models/page.py
zoho_creator_sdk/models/permissions.py
zoho_creator_sdk/models/reports.py
zoho_creator_sdk/models/response.py
zoho_creator_sdk/models/section.py
zoho_creator_sdk/models/workflows.py
zoho_creator_sdk-0.3.1.dist-info/licenses/LICENSE
zoho_creator_sdk-0.3.1.dist-info/METADATA
zoho_creator_sdk-0.3.1.dist-info/WHEEL
zoho_creator_sdk-0.3.1.dist-info/top_level.txt
zoho_creator_sdk-0.3.1.dist-info/RECORD
