Metadata-Version: 2.4
Name: zoho-creator-sdk
Version: 0.3.1
Summary: A modern Python SDK for the Zoho Creator API
Author-email: Carlos Paiva <2202731+carlospaiva@users.noreply.github.com>
License: MIT License
Project-URL: Documentation, https://github.com/carlospaiva/zoho-creator-sdk#readme
Project-URL: Homepage, https://github.com/carlospaiva/zoho-creator-sdk
Project-URL: Issues, https://github.com/carlospaiva/zoho-creator-sdk/issues
Project-URL: Repository, https://github.com/carlospaiva/zoho-creator-sdk
Keywords: zoho,zoho creator,zoho-creator-sdk,sdk,api,zoho creator api,python,httpx,pydantic
Classifier: Development Status :: 4 - Beta
Classifier: Intended Audience :: Developers
Classifier: License :: OSI Approved :: MIT License
Classifier: Programming Language :: Python :: 3
Classifier: Programming Language :: Python :: 3.8
Classifier: Programming Language :: Python :: 3.9
Classifier: Programming Language :: Python :: 3.10
Classifier: Programming Language :: Python :: 3.11
Classifier: Programming Language :: Python :: 3.12
Classifier: Programming Language :: Python :: 3.13
Classifier: Topic :: Software Development :: Libraries :: Python Modules
Requires-Python: >=3.8.1
License-File: LICENSE
Requires-Dist: dotenv>=0.9.9
Requires-Dist: httpx<1.0.0,>=0.23.0
Requires-Dist: pydantic<3.0.0,>=2.0.0
Requires-Dist: pydantic[email]<3.0.0,>=2.0.0
Requires-Dist: python-dateutil<3.0.0,>=2.8.0
Provides-Extra: dev
Requires-Dist: pytest<8.0.0,>=7.0.0; extra == "dev"
Requires-Dist: pytest-asyncio<1.0.0,>=0.21.0; extra == "dev"
Requires-Dist: pytest-cov<5.0.0,>=4.0.0; extra == "dev"
Requires-Dist: black<24.0.0,>=23.0.0; extra == "dev"
Requires-Dist: isort<6.0.0,>=5.12.0; extra == "dev"
Requires-Dist: mypy<2.0.0,>=1.0.0; extra == "dev"
Requires-Dist: flake8<7.0.0,>=6.0.0; extra == "dev"
Requires-Dist: pylint<4.0.0,>=3.2.0; extra == "dev"
Requires-Dist: build<2.0.0,>=1.0.0; extra == "dev"
Dynamic: license-file
